lark_bot_sdk/__init__.py
lark_bot_sdk/bot.py
lark_bot_sdk-0.1.1.dist-info/METADATA
lark_bot_sdk-0.1.1.dist-info/WHEEL
lark_bot_sdk-0.1.1.dist-info/top_level.txt
lark_bot_sdk-0.1.1.dist-info/RECORD
